polarization/__init__.py
polarization/__main__.py
polarization/jonesmatrix.py
polarization/jonesmatrixgroup.py
polarization/jonesvector.py
polarization/stokesvector.py
polarization/utils.py
polarization/vector.py
polarization-1.0.4.dist-info/LICENSE
polarization-1.0.4.dist-info/METADATA
polarization-1.0.4.dist-info/WHEEL
polarization-1.0.4.dist-info/top_level.txt
polarization-1.0.4.dist-info/RECORD
