Metadata-Version: 2.1
Name: polarization
Version: 1.0.4
Summary: Simple Jones vector and Jones matrices manipulation
Home-page: https://github.com/DCC-Lab/Polarization
Author: Daniel Cote
Author-email: dccote@cervo.ulaval.ca
License: MIT
Keywords: jones vector matrix polarization optics light
Platform: UNKNOWN
Classifier: Development Status :: 4 - Beta
Classifier: Intended Audience :: Science/Research
Classifier: Intended Audience :: Education
Classifier: Topic :: Scientific/Engineering :: Physics
Classifier: Topic :: Scientific/Engineering :: Visualization
Classifier: Topic :: Education
Classifier: License :: OSI Approved :: MIT License
Classifier: Programming Language :: Python
Classifier: Programming Language :: Python :: 3
Classifier: Programming Language :: Python :: 3.6
Classifier: Programming Language :: Python :: 3.7
Classifier: Programming Language :: Python :: 3.8
Classifier: Operating System :: OS Independent
Requires-Python: >=3.6
Requires-Dist: matplotlib (>=3)
Requires-Dist: numpy
